[{"MaMH":"sp1","TenMH":"sp1-ten","HanDungMH":"2021-12-12","CongTySX":"abc","NgaySX":"1997-10-14","Loai":"lh1","Gia":800000},{"MaMH":"sp2","TenMH":"sp2-ten","HanDungMH":"2022-05-08","CongTySX":"cde","NgaySX":"2022-05-08","Loai":"lh3","Gia":100},{"MaMH":"sp3","TenMH":"hji","HanDungMH":"2022-05-29","CongTySX":"cdefgh","NgaySX":"2022-05-01","Loai":"lh4","Gia":3000},{"MaMH":"sp22","TenMH":"aaa","HanDungMH":"2022-05-08","CongTySX":"abcghj","NgaySX":"2022-05-08","Loai":"lh6","Gia":10},{"MaMH":"sp10","TenMH":"122","HanDungMH":"1996-10-24","CongTySX":"1996","NgaySX":"2022-05-22","Loai":"lh1","Gia":100},{"MaMH":"sp4","TenMH":"sp4 ten","HanDungMH":"2022-05-20","CongTySX":"cde","NgaySX":"2022-04-01","Loai":"lh3","Gia":10000}]